{
	"products": [
		{	
			"id":0,
            "isTop":true,
            "isChecked":false,
            "name":"传感器",
            "model":"SD0123",
            "cate":"1",
            "people":"杨军",
            "editpeople":"杨军",
            "description":"这是一些描述！",
            "date":2141231198432
        },
        {   
            "id":1,
            "isTop":false,
            "isChecked":false,
            "name":"手机",
            "model":"SD0123",
            "cate":"1",
            "people":"杨军",
            "editpeople":"杨军",
            "description":"这是一些描述！",
            "date":2141231198432
        },
        {   
            "id":2,
            "isTop":false,
            "isChecked":false,
            "name":"蓝牙设备",
            "model":"SD0123",
            "cate":"1",
            "people":"杨军",
            "editpeople":"杨军",
            "description":"这是一些描述！",
            "date":2141231198432
        },
        {   
            "id":3,
            "isTop":true,
            "isChecked":false,
            "name":"屏幕",
            "model":"SD0123",
            "cate":"1",
            "people":"杨军",
            "editpeople":"杨军",
            "description":"这是一些描述！",
            "date":2141231198432
        }
	]
}